[
  {
    "variableName": "_templateService",
    "variableType": "TemplateApiService",
    "mockedClass": "TemplateApiService",
    "isReuseableMock": "Fully Shared",
    "mockPattern": "Creation:\n\u2014 Attribute Mock Creation\n\nStubbing:\n\u2014 None\n\nVerification:\n\u2014 None",
    "classContext": {
      "packageName": "org.apache.cloudstack.api.command.user.template",
      "filePath": "C:\\java tool\\Apache\\cloudstack\\api\\src\\test\\java\\org\\apache\\cloudstack\\api\\command\\user\\template\\CopyTemplateCmdByAdminTest.java",
      "className": "CopyTemplateCmdByAdminTest"
    },
    "statements": [
      {
        "type": "FIELD_MOCK_CREATION",
        "code": "@Mock\r\npublic TemplateApiService _templateService;",
        "line": 44,
        "locate": "Attribute",
        "locationContext": {
          "methodName": "[FieldDeclaration]",
          "methodAnnotations": [
            "@Mock"
          ]
        }
      }
    ],
    "pattern_id": 3
  },
  {
    "variableName": "_templateService",
    "variableType": "TemplateApiService",
    "mockedClass": "TemplateApiService",
    "isReuseableMock": "Fully Shared",
    "mockPattern": "Creation:\n\u2014 Attribute Mock Creation\n\nStubbing:\n\u2014 None\n\nVerification:\n\u2014 None",
    "classContext": {
      "packageName": "org.apache.cloudstack.api.command.user.template",
      "filePath": "C:\\java tool\\Apache\\cloudstack\\api\\src\\test\\java\\org\\apache\\cloudstack\\api\\command\\user\\template\\CopyTemplateCmdTest.java",
      "className": "CopyTemplateCmdTest"
    },
    "statements": [
      {
        "type": "FIELD_MOCK_CREATION",
        "code": "@Mock\r\npublic TemplateApiService _templateService;",
        "line": 42,
        "locate": "Attribute",
        "locationContext": {
          "methodName": "[FieldDeclaration]",
          "methodAnnotations": [
            "@Mock"
          ]
        }
      }
    ],
    "pattern_id": 3
  },
  {
    "variableName": "_templateService",
    "variableType": "TemplateApiService",
    "mockedClass": "TemplateApiService",
    "isReuseableMock": "Fully Shared",
    "mockPattern": "Creation:\n\u2014 Attribute Mock Creation\n\nStubbing:\n\u2014 None\n\nVerification:\n\u2014 None",
    "classContext": {
      "packageName": "org.apache.cloudstack.api.command.user.template",
      "filePath": "C:\\java tool\\Apache\\cloudstack\\api\\src\\test\\java\\org\\apache\\cloudstack\\api\\command\\user\\template\\RegisterTemplateCmdByAdminTest.java",
      "className": "RegisterTemplateCmdByAdminTest"
    },
    "statements": [
      {
        "type": "FIELD_MOCK_CREATION",
        "code": "@Mock\r\npublic TemplateApiService _templateService;",
        "line": 41,
        "locate": "Attribute",
        "locationContext": {
          "methodName": "[FieldDeclaration]",
          "methodAnnotations": [
            "@Mock"
          ]
        }
      }
    ],
    "pattern_id": 3
  },
  {
    "variableName": "_templateService",
    "variableType": "TemplateApiService",
    "mockedClass": "TemplateApiService",
    "isReuseableMock": "Fully Shared",
    "mockPattern": "Creation:\n\u2014 Attribute Mock Creation\n\nStubbing:\n\u2014 None\n\nVerification:\n\u2014 None",
    "classContext": {
      "packageName": "org.apache.cloudstack.api.command.user.template",
      "filePath": "C:\\java tool\\Apache\\cloudstack\\api\\src\\test\\java\\org\\apache\\cloudstack\\api\\command\\user\\template\\RegisterTemplateCmdTest.java",
      "className": "RegisterTemplateCmdTest"
    },
    "statements": [
      {
        "type": "FIELD_MOCK_CREATION",
        "code": "@Mock\r\npublic TemplateApiService _templateService;",
        "line": 41,
        "locate": "Attribute",
        "locationContext": {
          "methodName": "[FieldDeclaration]",
          "methodAnnotations": [
            "@Mock"
          ]
        }
      }
    ],
    "pattern_id": 3
  },
  {
    "variableName": "_templateService",
    "variableType": "TemplateApiService",
    "mockedClass": "TemplateApiService",
    "isReuseableMock": "Fully Shared",
    "mockPattern": "Creation:\n\u2014 Attribute Mock Creation\n\nStubbing:\n\u2014 None\n\nVerification:\n\u2014 None",
    "classContext": {
      "packageName": "org.apache.cloudstack.api.command.user.userdata",
      "filePath": "C:\\java tool\\Apache\\cloudstack\\api\\src\\test\\java\\org\\apache\\cloudstack\\api\\command\\user\\userdata\\LinkUserDataToTemplateCmdTest.java",
      "className": "LinkUserDataToTemplateCmdTest"
    },
    "statements": [
      {
        "type": "FIELD_MOCK_CREATION",
        "code": "@Mock\r\nTemplateApiService _templateService;",
        "line": 57,
        "locate": "Attribute",
        "locationContext": {
          "methodName": "[FieldDeclaration]",
          "methodAnnotations": [
            "@Mock"
          ]
        }
      }
    ],
    "pattern_id": 3
  }
]