[
  {
    "variableName": "INPUT_ROW2",
    "variableType": "InputRow",
    "mockedClass": "InputRow",
    "isReuseableMock": false,
    "mockPattern": "Creation:\n\u2014 Attribute Mock Creation\n\nStubbing:\n\u2014 None\n\nVerification:\n\u2014 None",
    "classContext": {
      "packageName": "org.apache.druid.data.input",
      "filePath": "C:\\java tool\\Apache\\druid\\processing\\src\\test\\java\\org\\apache\\druid\\data\\input\\HandlingInputRowIteratorTest.java",
      "className": "PresentRowTest"
    },
    "statements": [
      {
        "type": "FIELD_MOCK_CREATION",
        "code": "private static final InputRow INPUT_ROW2 = mock(InputRow.class);",
        "line": 91,
        "locate": "Attribute",
        "locationContext": {
          "methodName": "[FieldDeclaration]",
          "methodAnnotations": []
        }
      }
    ],
    "pattern_id": 3
  },
  {
    "variableName": "INPUT_ROW1",
    "variableType": "InputRow",
    "mockedClass": "InputRow",
    "isReuseableMock": false,
    "mockPattern": "Creation:\n\u2014 Attribute Mock Creation\n\nStubbing:\n\u2014 None\n\nVerification:\n\u2014 None",
    "classContext": {
      "packageName": "org.apache.druid.data.input",
      "filePath": "C:\\java tool\\Apache\\druid\\processing\\src\\test\\java\\org\\apache\\druid\\data\\input\\HandlingInputRowIteratorTest.java",
      "className": "PresentRowTest"
    },
    "statements": [
      {
        "type": "FIELD_MOCK_CREATION",
        "code": "private static final InputRow INPUT_ROW1 = mock(InputRow.class);",
        "line": 90,
        "locate": "Attribute",
        "locationContext": {
          "methodName": "[FieldDeclaration]",
          "methodAnnotations": []
        }
      }
    ],
    "pattern_id": 3
  }
]