[
  {
    "variableName": "taskExecutorDelegate",
    "variableType": "AsyncTaskExecutor",
    "mockedClass": "AsyncTaskExecutor",
    "isReuseableMock": false,
    "mockPattern": "Creation:\n\u2014 Attribute Mock Creation\n\nStubbing:\n\u2014 None\n\nVerification:\n\u2014 None",
    "classContext": {
      "packageName": "org.springframework.security.task",
      "filePath": "C:\\java tool\\Spring\\spring-security\\core\\src\\test\\java\\org\\springframework\\security\\task\\AbstractDelegatingSecurityContextAsyncTaskExecutorTests.java",
      "className": "AbstractDelegatingSecurityContextAsyncTaskExecutorTests"
    },
    "statements": [
      {
        "type": "FIELD_MOCK_CREATION",
        "code": "@Mock\r\nprotected AsyncTaskExecutor taskExecutorDelegate;",
        "line": 41,
        "locate": "Attribute",
        "locationContext": {
          "methodName": "[FieldDeclaration]",
          "methodAnnotations": [
            "@Mock"
          ]
        }
      }
    ],
    "pattern_id": 3
  }
]