[
  {
    "variableName": "authValidator",
    "variableType": "AuthValidator",
    "mockedClass": "AuthValidator",
    "isReuseableMock": false,
    "mockPattern": "Creation:\n\u2014 Attribute Mock Creation\n\nStubbing:\n\u2014 None\n\nVerification:\n\u2014 None",
    "classContext": {
      "packageName": "org.apache.druid.security.authentication",
      "filePath": "C:\\java tool\\Apache\\druid\\extensions-core\\druid-basic-security\\src\\test\\java\\org\\apache\\druid\\security\\authentication\\CoordinatorBasicAuthenticatorResourceTest.java",
      "className": "CoordinatorBasicAuthenticatorResourceTest"
    },
    "statements": [
      {
        "type": "FIELD_MOCK_CREATION",
        "code": "@Mock\r\nprivate AuthValidator authValidator;",
        "line": 69,
        "locate": "Attribute",
        "locationContext": {
          "methodName": "[FieldDeclaration]",
          "methodAnnotations": [
            "@Mock"
          ]
        }
      }
    ],
    "pattern_id": 3
  },
  {
    "variableName": "authValidator",
    "variableType": "AuthValidator",
    "mockedClass": "AuthValidator",
    "isReuseableMock": false,
    "mockPattern": "Creation:\n\u2014 Attribute Mock Creation\n\nStubbing:\n\u2014 None\n\nVerification:\n\u2014 None",
    "classContext": {
      "packageName": "org.apache.druid.security.authorization",
      "filePath": "C:\\java tool\\Apache\\druid\\extensions-core\\druid-basic-security\\src\\test\\java\\org\\apache\\druid\\security\\authorization\\CoordinatorBasicAuthorizerResourceTest.java",
      "className": "CoordinatorBasicAuthorizerResourceTest"
    },
    "statements": [
      {
        "type": "FIELD_MOCK_CREATION",
        "code": "@Mock\r\nprivate AuthValidator authValidator;",
        "line": 86,
        "locate": "Attribute",
        "locationContext": {
          "methodName": "[FieldDeclaration]",
          "methodAnnotations": [
            "@Mock"
          ]
        }
      }
    ],
    "pattern_id": 3
  },
  {
    "variableName": "authValidator",
    "variableType": "AuthValidator",
    "mockedClass": "AuthValidator",
    "isReuseableMock": false,
    "mockPattern": "Creation:\n\u2014 Attribute Mock Creation\n\nStubbing:\n\u2014 None\n\nVerification:\n\u2014 None",
    "classContext": {
      "packageName": "org.apache.druid.security.basic.authentication.endpoint",
      "filePath": "C:\\java tool\\Apache\\druid\\extensions-core\\druid-basic-security\\src\\test\\java\\org\\apache\\druid\\security\\basic\\authentication\\endpoint\\BasicAuthenticatorResourceTest.java",
      "className": "BasicAuthenticatorResourceTest"
    },
    "statements": [
      {
        "type": "FIELD_MOCK_CREATION",
        "code": "@Mock\r\nprivate AuthValidator authValidator;",
        "line": 45,
        "locate": "Attribute",
        "locationContext": {
          "methodName": "[FieldDeclaration]",
          "methodAnnotations": [
            "@Mock"
          ]
        }
      }
    ],
    "pattern_id": 3
  },
  {
    "variableName": "authValidator",
    "variableType": "AuthValidator",
    "mockedClass": "AuthValidator",
    "isReuseableMock": false,
    "mockPattern": "Creation:\n\u2014 Attribute Mock Creation\n\nStubbing:\n\u2014 None\n\nVerification:\n\u2014 None",
    "classContext": {
      "packageName": "org.apache.druid.security.basic.authorization.endpoint",
      "filePath": "C:\\java tool\\Apache\\druid\\extensions-core\\druid-basic-security\\src\\test\\java\\org\\apache\\druid\\security\\basic\\authorization\\endpoint\\BasicAuthorizerResourceTest.java",
      "className": "BasicAuthorizerResourceTest"
    },
    "statements": [
      {
        "type": "FIELD_MOCK_CREATION",
        "code": "@Mock\r\nprivate AuthValidator authValidator;",
        "line": 51,
        "locate": "Attribute",
        "locationContext": {
          "methodName": "[FieldDeclaration]",
          "methodAnnotations": [
            "@Mock"
          ]
        }
      }
    ],
    "pattern_id": 3
  }
]