[
  {
    "variableName": "requestAdapter",
    "variableType": "RequestAdapter",
    "mockedClass": "RequestAdapter",
    "isReuseableMock": false,
    "mockPattern": "Creation:\n\u2014 Local Mock Creation in Test Case\n\nStubbing:\n\u2014 None\n\nVerification:\n\u2014 None",
    "classContext": {
      "packageName": "com.microsoft.kiota",
      "filePath": "C:\\java tool\\Microsoft\\kiota-java\\components\\abstractions\\src\\test\\java\\com\\microsoft\\kiota\\MultiPartBodyTest.java",
      "className": "MultiPartBodyTest"
    },
    "statements": [
      {
        "type": "DECLARATION",
        "code": "final RequestAdapter requestAdapter = mock(RequestAdapter.class);",
        "line": 45,
        "locate": "Test Case",
        "locationContext": {
          "methodName": "requiresPartsForSerialization",
          "methodAnnotations": [
            "@Test"
          ]
        }
      }
    ],
    "pattern_id": 2
  },
  {
    "variableName": "requestAdapter",
    "variableType": "RequestAdapter",
    "mockedClass": "RequestAdapter",
    "isReuseableMock": false,
    "mockPattern": "Creation:\n\u2014 Local Mock Creation in Test Case\n\nStubbing:\n\u2014 None\n\nVerification:\n\u2014 None",
    "classContext": {
      "packageName": "com.microsoft.kiota",
      "filePath": "C:\\java tool\\Microsoft\\kiota-java\\components\\abstractions\\src\\test\\java\\com\\microsoft\\kiota\\MultiPartBodyTest.java",
      "className": "MultiPartBodyTest"
    },
    "statements": [
      {
        "type": "DECLARATION",
        "code": "final RequestAdapter requestAdapter = mock(RequestAdapter.class);",
        "line": 53,
        "locate": "Test Case",
        "locationContext": {
          "methodName": "addsPart",
          "methodAnnotations": [
            "@Test"
          ]
        }
      }
    ],
    "pattern_id": 2
  },
  {
    "variableName": "requestAdapter",
    "variableType": "RequestAdapter",
    "mockedClass": "RequestAdapter",
    "isReuseableMock": false,
    "mockPattern": "Creation:\n\u2014 Local Mock Creation in Test Case\n\nStubbing:\n\u2014 None\n\nVerification:\n\u2014 None",
    "classContext": {
      "packageName": "com.microsoft.kiota",
      "filePath": "C:\\java tool\\Microsoft\\kiota-java\\components\\abstractions\\src\\test\\java\\com\\microsoft\\kiota\\MultiPartBodyTest.java",
      "className": "MultiPartBodyTest"
    },
    "statements": [
      {
        "type": "DECLARATION",
        "code": "final RequestAdapter requestAdapter = mock(RequestAdapter.class);",
        "line": 64,
        "locate": "Test Case",
        "locationContext": {
          "methodName": "removesPart",
          "methodAnnotations": [
            "@Test"
          ]
        }
      }
    ],
    "pattern_id": 2
  }
]