[
  {
    "variableName": "_clusterDetailsDao",
    "variableType": "ClusterDetailsDao",
    "mockedClass": "ClusterDetailsDao",
    "isReuseableMock": "Hybrid",
    "mockPattern": "Creation:\n\u2014 Attribute Mock Creation\n\nStubbing:\n\u2014 Test Case\n\nVerification:\n\u2014 None",
    "classContext": {
      "packageName": "com.cloud.vm",
      "filePath": "C:\\java tool\\Apache\\cloudstack\\engine\\orchestration\\src\\test\\java\\com\\cloud\\vm\\VirtualMachineManagerImplTest.java",
      "className": "VirtualMachineManagerImplTest"
    },
    "statements": [
      {
        "type": "FIELD_MOCK_CREATION",
        "code": "@Mock\r\nprivate ClusterDetailsDao _clusterDetailsDao;",
        "line": 190,
        "locate": "Attribute",
        "locationContext": {
          "methodName": "[FieldDeclaration]",
          "methodAnnotations": [
            "@Mock"
          ]
        }
      },
      {
        "type": "STUBBING",
        "code": "when(_clusterDetailsDao.findDetail(1L, VmDetailConstants.CPU_OVER_COMMIT_RATIO)).thenReturn(cluster_detail_cpu);",
        "line": 1009,
        "locate": "Test Case",
        "locationContext": {
          "methodName": "testOrchestrateStartNonNullPodId",
          "methodAnnotations": [
            "@Test"
          ]
        }
      },
      {
        "type": "STUBBING",
        "code": "when(_clusterDetailsDao.findDetail(1L, VmDetailConstants.MEMORY_OVER_COMMIT_RATIO)).thenReturn(cluster_detail_ram);",
        "line": 1010,
        "locate": "Test Case",
        "locationContext": {
          "methodName": "testOrchestrateStartNonNullPodId",
          "methodAnnotations": [
            "@Test"
          ]
        }
      },
      {
        "type": "STUBBING",
        "code": "when(_clusterDetailsDao.findDetail(1L, VmDetailConstants.CPU_OVER_COMMIT_RATIO)).thenReturn(cluster_detail_cpu);",
        "line": 1101,
        "locate": "Test Case",
        "locationContext": {
          "methodName": "testOrchestrateStartNullPodId",
          "methodAnnotations": [
            "@Test"
          ]
        }
      },
      {
        "type": "STUBBING",
        "code": "when(_clusterDetailsDao.findDetail(1L, VmDetailConstants.MEMORY_OVER_COMMIT_RATIO)).thenReturn(cluster_detail_ram);",
        "line": 1102,
        "locate": "Test Case",
        "locationContext": {
          "methodName": "testOrchestrateStartNullPodId",
          "methodAnnotations": [
            "@Test"
          ]
        }
      }
    ],
    "pattern_id": 4
  }
]