[
  {
    "variableName": "volumeVO",
    "variableType": "VolumeVO",
    "mockedClass": "VolumeVO",
    "isReuseableMock": false,
    "mockPattern": "Creation:\n\u2014 Local Mock Creation in Helper\n\nStubbing:\n\u2014 Helper Method\n\nVerification:\n\u2014 None",
    "classContext": {
      "packageName": "org.apache.cloudstack.storage.snapshot",
      "filePath": "C:\\java tool\\Apache\\cloudstack\\engine\\storage\\snapshot\\src\\test\\java\\org\\apache\\cloudstack\\storage\\snapshot\\CephSnapshotStrategyTest.java",
      "className": "CephSnapshotStrategyTest"
    },
    "statements": [
      {
        "type": "DECLARATION",
        "code": "VolumeVO volumeVO = Mockito.mock(VolumeVO.class);",
        "line": 81,
        "locate": "Helper Method",
        "locationContext": {
          "methodName": "configureAndVerifyCanHandle",
          "methodAnnotations": []
        }
      },
      {
        "type": "STUBBING",
        "code": "Mockito.when(volumeVO.getRemoved()).thenReturn(removed);",
        "line": 82,
        "locate": "Helper Method",
        "locationContext": {
          "methodName": "configureAndVerifyCanHandle",
          "methodAnnotations": []
        }
      }
    ],
    "pattern_id": 10
  }
]